yte/__init__.py
yte/code_handler.py
yte/context.py
yte/document.py
yte/exceptions.py
yte/process.py
yte/value_handler.py
yte-1.8.0.dist-info/LICENSE
yte-1.8.0.dist-info/METADATA
yte-1.8.0.dist-info/WHEEL
yte-1.8.0.dist-info/entry_points.txt
yte-1.8.0.dist-info/RECORD
