Metadata-Version: 2.3
Name: yte
Version: 1.8.0
Summary: A YAML template engine with Python expressions
License: MIT
Author: Johannes Köster
Author-email: johannes.koester@tu-dortmund.de
Requires-Python: >=3.7,<4.0
Classifier: License :: OSI Approved :: MIT License
Classifier: Programming Language :: Python :: 3
Classifier: Programming Language :: Python :: 3.7
Classifier: Programming Language :: Python :: 3.8
Classifier: Programming Language :: Python :: 3.9
Classifier: Programming Language :: Python :: 3.10
Classifier: Programming Language :: Python :: 3.11
Classifier: Programming Language :: Python :: 3.12
Classifier: Programming Language :: Python :: 3.13
Requires-Dist: dpath (>=2.1,<3.0)
Requires-Dist: plac (>=1.3.4,<2.0)
Requires-Dist: pyyaml (>=6.0,<7.0)
Project-URL: Homepage, https://github.com/yte-template-engine/yte
Project-URL: Repository, https://github.com/yte-template-engine/yte
